{"cameraMode":{"drawMode":0,"name":"Shaded","section":"Shading Mode"},"sceneLighting":true,"audioPlay":false,"sceneViewState":{"m_AlwaysRefresh":false,"showFog":false,"showSkybox":false,"showFlares":false,"showImageEffects":false,"showParticleSystems":false,"showVisualEffectGraphs":true,"m_FxEnabled":false},"in2DMode":false,"pivot":{"x":-3.390646457672119,"y":-0.3711128234863281,"z":-4.151410102844238},"rotation":{"x":0.4378281235694885,"y":-0.44593846797943118,"z":0.2660859227180481,"w":0.7339500784873962},"size":6.815089225769043,"orthographic":false}