{"cameraMode":{"drawMode":0,"name":"Shaded","section":"Shading Mode"},"sceneLighting":true,"audioPlay":false,"sceneViewState":{"m_AlwaysRefresh":false,"showFog":false,"showSkybox":false,"showFlares":false,"showImageEffects":false,"showParticleSystems":false,"showVisualEffectGraphs":true,"m_FxEnabled":false},"in2DMode":false,"pivot":{"x":-5.133694171905518,"y":-98.17158508300781,"z":-3.998697280883789},"rotation":{"x":0.6330872178077698,"y":-0.2771673798561096,"z":0.2602337598800659,"w":0.6742828488349915},"size":52.65677261352539,"orthographic":false}